.DS_Store
MarketClient/__init__.py
market_client-0.0.1.dist-info/METADATA
market_client-0.0.1.dist-info/WHEEL
market_client-0.0.1.dist-info/top_level.txt
market_client-0.0.1.dist-info/RECORD
