Metadata-Version: 2.1
Name: market-client
Version: 0.0.1
Summary: Client for the Birds.ai Market server
Home-page: https://gitlab.com/janerikvw/market-client
Author: Jan Erik van Woerden
Author-email: janerik@birds.ai
License: UNKNOWN
Platform: UNKNOWN
Classifier: Programming Language :: Python :: 3
Classifier: License :: OSI Approved :: MIT License
Classifier: Operating System :: OS Independent
